sandyie_read/__init__.py
sandyie_read/exceptions.py
sandyie_read/logging_config.py
sandyie_read/registry.py
sandyie_read/utils.py
sandyie_read/readers/__init__.py
sandyie_read/readers/base.py
sandyie_read/readers/bin_reader.py
sandyie_read/readers/csv_reader.py
sandyie_read/readers/docx_reader.py
sandyie_read/readers/excel_reader.py
sandyie_read/readers/html_reader.py
sandyie_read/readers/image_reader.py
sandyie_read/readers/js_reader.py
sandyie_read/readers/json_reader.py
sandyie_read/readers/markdown_reader.py
sandyie_read/readers/ocr_reader.py
sandyie_read/readers/parquet_reader.py
sandyie_read/readers/pdf_reader.py
sandyie_read/readers/pickle_reader.py
sandyie_read/readers/svg_reader.py
sandyie_read/readers/tsv_reader.py
sandyie_read/readers/txt_reader.py
sandyie_read/readers/yaml_reader.py
sandyie_read/readers/zip_reader.py
sandyie_read-1.2.1.dist-info/licenses/LICENSE
sandyie_read-1.2.1.dist-info/METADATA
sandyie_read-1.2.1.dist-info/WHEEL
sandyie_read-1.2.1.dist-info/top_level.txt
sandyie_read-1.2.1.dist-info/RECORD
