Metadata-Version: 2.4
Name: sandyie_read
Version: 1.2.1
Summary: A lightweight Python library to read various data formats including PDF, images, YAML, and more.
Home-page: https://github.com/SanjayDK3669/sandyie_read
Author: Sandyie
Author-email: business@sandyie.in
License: MIT
Classifier: Development Status :: 4 - Beta
Classifier: Intended Audience :: Developers
Classifier: Intended Audience :: Science/Research
Classifier: License :: OSI Approved :: MIT License
Classifier: Operating System :: OS Independent
Classifier: Programming Language :: Python :: 3
Classifier: Programming Language :: Python :: 3.7
Classifier: Programming Language :: Python :: 3.8
Classifier: Programming Language :: Python :: 3.9
Classifier: Programming Language :: Python :: 3.10
Classifier: Programming Language :: Python :: 3.11
Classifier: Programming Language :: Python :: 3.12
Classifier: Programming Language :: Python :: 3.13
Classifier: Topic :: Software Development :: Libraries :: Python Modules
Classifier: Topic :: Text Processing :: General
Classifier: Topic :: Scientific/Engineering :: Information Analysis
Requires-Python: >=3.7, <3.14
License-File: LICENSE
Requires-Dist: pandas<2.3,>=2.1.0
Requires-Dist: numpy>=1.21.0
Requires-Dist: pyarrow>=12.0.0
Requires-Dist: scipy<1.11,>=1.7.0; python_version < "3.11"
Requires-Dist: scipy<1.15,>=1.7.0; python_version >= "3.11" and python_version < "3.14"
Requires-Dist: python-docx>=0.8.11
Requires-Dist: opencv-python
Requires-Dist: PyMuPDF
Requires-Dist: pytesseract
Requires-Dist: PyYAML
Requires-Dist: Pillow
Requires-Dist: pdfplumber
Requires-Dist: openpyxl
Requires-Dist: beautifulsoup4>=4.9.0
Requires-Dist: scikit-learn>=1.0
Dynamic: author
Dynamic: author-email
Dynamic: classifier
Dynamic: description
Dynamic: description-content-type
Dynamic: home-page
Dynamic: license
Dynamic: license-file
Dynamic: requires-dist
Dynamic: requires-python
Dynamic: summary
